hcmioptim/__init__.py
hcmioptim/_optim_types.py
hcmioptim/ga.py
hcmioptim/sa.py
hcmioptim/ga/__init__.py
hcmioptim/ga/_ga.py
hcmioptim/sa/__init__.py
hcmioptim/sa/_sa.py
hcmioptim-0.0.13.dist-info/LICENSE
hcmioptim-0.0.13.dist-info/METADATA
hcmioptim-0.0.13.dist-info/WHEEL
hcmioptim-0.0.13.dist-info/top_level.txt
hcmioptim-0.0.13.dist-info/RECORD
