Metadata-Version: 2.1
Name: hcmioptim
Version: 0.0.13
Summary: A collection of useful heuristic based optimization algorithms.
Home-page: UNKNOWN
License: GNU GPLv3
Platform: UNKNOWN
Classifier: Programming Language :: Python :: 3
Requires-Dist: numpy
